README.rst
setup.py
src/aliyun_openapi_python_sdk_managed_credentials_provider.egg-info/PKG-INFO
src/aliyun_openapi_python_sdk_managed_credentials_provider.egg-info/SOURCES.txt
src/aliyun_openapi_python_sdk_managed_credentials_provider.egg-info/dependency_links.txt
src/aliyun_openapi_python_sdk_managed_credentials_provider.egg-info/requires.txt
src/aliyun_openapi_python_sdk_managed_credentials_provider.egg-info/top_level.txt
src/aliyun_sdk_secretsmanager_sdk_core_plugin/__init__.py
src/aliyun_sdk_secretsmanager_sdk_core_plugin/proxy_acs_client.py
src/aliyun_sdk_secretsmanager_sdk_core_plugin/sdk_core_ak_expire_handler.py
src/aliyun_sdk_secretsmanager_sdk_core_plugin/sdk_core_temp_ak_expire_handler.py
src/aliyun_sdk_secretsmanager_sdk_core_plugin/secretsmanager_sdk_core_plugin_credential_updater.py
src/aliyun_sdk_secretsmanager_sdk_core_plugin/secretsmanager_sdk_core_plugin_manager.py